sasa/__init__.py
sasa/classifier.py
sasa/gflags.py
sasa/happyfuntokenizing.py
sasa/htmlentitydefs.py
sasa/normalizer.py
sasa/sentiment.py
sasa/tokenizer.py
sasa/models/model.unigram.nb.bool.politics
sasa/models/model.unigram.nb.bool.politics.positivebias
sasa/models/model.unigram.nb.bool.politics.unbiased
sasa-0.2.0.dist-info/METADATA
sasa-0.2.0.dist-info/WHEEL
sasa-0.2.0.dist-info/top_level.txt
sasa-0.2.0.dist-info/RECORD
