Metadata-Version: 2.1
Name: sasa
Version: 0.2.0
Summary: SAIL/AIL Sentiment Analyzer
Home-page: https://code.google.com/p/sasa-tool/
Author: Abe Kazemzadeh
Author-email: kazemzad@usc.edu
License: apache 2.0
Platform: UNKNOWN
Classifier: Development Status :: 2 - Pre-Alpha
Classifier: Environment :: Console
Classifier: Intended Audience :: Science/Research
Classifier: License :: OSI Approved :: Apache Software License
Classifier: Natural Language :: English
Classifier: Topic :: Communications
Classifier: Topic :: Scientific/Engineering :: Artificial Intelligence
Classifier: Topic :: Scientific/Engineering :: Human Machine Interfaces
Classifier: Topic :: Scientific/Engineering :: Information Analysis
Classifier: Topic :: Sociology
Classifier: Topic :: Text Processing :: Linguistic
Requires-Dist: nltk (>=3.4)
